cylc/flow/__init__.py
cylc/flow/async_util.py
cylc/flow/broadcast_mgr.py
cylc/flow/broadcast_report.py
cylc/flow/c3mro.py
cylc/flow/clean.py
cylc/flow/command_polling.py
cylc/flow/command_validation.py
cylc/flow/commands.py
cylc/flow/config.py
cylc/flow/context_node.py
cylc/flow/cylc_subproc.py
cylc/flow/daemonize.py
cylc/flow/data_messages_pb2.py
cylc/flow/data_messages_pb2.pyi
cylc/flow/data_store_mgr.py
cylc/flow/dbstatecheck.py
cylc/flow/exceptions.py
cylc/flow/flags.py
cylc/flow/flow_mgr.py
cylc/flow/graph_parser.py
cylc/flow/graphnode.py
cylc/flow/host_select.py
cylc/flow/hostuserutil.py
cylc/flow/id.py
cylc/flow/id_cli.py
cylc/flow/id_match.py
cylc/flow/install.py
cylc/flow/job_file.py
cylc/flow/job_runner_mgr.py
cylc/flow/listify.py
cylc/flow/log_diagnosis.py
cylc/flow/log_level.py
cylc/flow/loggingutil.py
cylc/flow/option_parsers.py
cylc/flow/param_expand.py
cylc/flow/pathutil.py
cylc/flow/pipe_poller.py
cylc/flow/platforms.py
cylc/flow/plugins.py
cylc/flow/prerequisite.py
cylc/flow/print_tree.py
cylc/flow/profiler.py
cylc/flow/py.typed
cylc/flow/remote.py
cylc/flow/resources.py
cylc/flow/rundb.py
cylc/flow/scheduler.py
cylc/flow/scheduler_cli.py
cylc/flow/subprocctx.py
cylc/flow/subprocpool.py
cylc/flow/task_action_timer.py
cylc/flow/task_events_mgr.py
cylc/flow/task_id.py
cylc/flow/task_job_logs.py
cylc/flow/task_job_mgr.py
cylc/flow/task_message.py
cylc/flow/task_outputs.py
cylc/flow/task_pool.py
cylc/flow/task_proxy.py
cylc/flow/task_qualifiers.py
cylc/flow/task_remote_cmd.py
cylc/flow/task_remote_mgr.py
cylc/flow/task_state.py
cylc/flow/task_state_prop.py
cylc/flow/task_trigger.py
cylc/flow/taskdef.py
cylc/flow/templatevars.py
cylc/flow/terminal.py
cylc/flow/time_parser.py
cylc/flow/timer.py
cylc/flow/unicode_rules.py
cylc/flow/util.py
cylc/flow/wallclock.py
cylc/flow/workflow_db_mgr.py
cylc/flow/workflow_events.py
cylc/flow/workflow_files.py
cylc/flow/workflow_status.py
cylc/flow/xtrigger_mgr.py
cylc/flow/cfgspec/__init__.py
cylc_flow-8.6.2.dist-info/licenses/COPYING
cylc_flow-8.6.2.dist-info/METADATA
cylc_flow-8.6.2.dist-info/WHEEL
cylc_flow-8.6.2.dist-info/entry_points.txt
cylc_flow-8.6.2.dist-info/top_level.txt
cylc_flow-8.6.2.dist-info/RECORD
