Metadata-Version: 2.4
Name: cylc-flow
Version: 8.6.2
Summary: A workflow engine for cycling systems
Home-page: https://cylc.org/
Author: Hilary Oliver
License: GPL
Project-URL: Documentation, https://cylc.github.io/cylc-doc/stable/html/index.html
Project-URL: Source, https://github.com/cylc/cylc-flow
Project-URL: Tracker, https://github.com/cylc/cylc-flow/issues
Keywords: cycling-workflows,hpc,job-scheduler,metascheduler,workflow-automation,workflow-engine,workflow-management,scheduling
Platform: any
Classifier: Environment :: Console
Classifier: Environment :: Web Environment
Classifier: Intended Audience :: Developers
Classifier: Intended Audience :: System Administrators
Classifier: Intended Audience :: Science/Research
Classifier: License :: OSI Approved :: GNU General Public License v3 (GPLv3)
Classifier: Operating System :: POSIX :: Linux
Classifier: Programming Language :: Python
Classifier: Programming Language :: Python :: 3.12
Classifier: Programming Language :: Python :: 3.13
Classifier: Programming Language :: Python :: 3 :: Only
Classifier: Programming Language :: Python :: Implementation :: CPython
Classifier: Topic :: Scientific/Engineering :: Atmospheric Science
Requires-Python: >=3.12
License-File: COPYING
Requires-Dist: ansimarkup>=1.0.0
Requires-Dist: colorama<1,>=0.4
Requires-Dist: graphql-core<3.3,>=3.2
Requires-Dist: graphene<3.5,>=3.4.0
Requires-Dist: jinja2==3.0.*
Requires-Dist: metomi-isodatetime<1!3.2.0,>=1!3.0.0
Requires-Dist: packaging
Requires-Dist: protobuf<8,>=5
Requires-Dist: psutil>=5.6.0
Requires-Dist: pyzmq>=22
Requires-Dist: urwid!=2.6.2,!=2.6.3,<4,>=2.2
Provides-Extra: graph
Requires-Dist: pillow; extra == "graph"
Provides-Extra: main-loop-log-data-store
Requires-Dist: pympler; extra == "main-loop-log-data-store"
Requires-Dist: matplotlib; extra == "main-loop-log-data-store"
Provides-Extra: main-loop-log-main-loop
Requires-Dist: matplotlib; extra == "main-loop-log-main-loop"
Provides-Extra: main-loop-log-memory
Requires-Dist: pympler; extra == "main-loop-log-memory"
Requires-Dist: matplotlib; extra == "main-loop-log-memory"
Provides-Extra: main-loop-log-db
Requires-Dist: sqlparse; extra == "main-loop-log-db"
Provides-Extra: report-timings
Requires-Dist: pandas==1.*; extra == "report-timings"
Requires-Dist: matplotlib; extra == "report-timings"
Provides-Extra: tests
Requires-Dist: aiosmtpd; extra == "tests"
Requires-Dist: async_generator; extra == "tests"
Requires-Dist: bandit>=1.7.0; extra == "tests"
Requires-Dist: coverage>=7.9.0; extra == "tests"
Requires-Dist: flake8-broken-line>=0.3.0; extra == "tests"
Requires-Dist: flake8-bugbear>=21.0.0; extra == "tests"
Requires-Dist: flake8-builtins>=1.5.0; extra == "tests"
Requires-Dist: flake8-comprehensions>=3.5.0; extra == "tests"
Requires-Dist: flake8-debugger>=4.0.0; extra == "tests"
Requires-Dist: flake8-implicit-str-concat>=0.4; extra == "tests"
Requires-Dist: flake8-mutable>=1.2.0; extra == "tests"
Requires-Dist: flake8-simplify>=0.14.0; python_version < "3.14" and extra == "tests"
Requires-Dist: flake8-type-checking; extra == "tests"
Requires-Dist: flake8>=3.0.0; extra == "tests"
Requires-Dist: mypy>=0.910; extra == "tests"
Requires-Dist: pytest-asyncio!=0.23.*,>=0.21.2; extra == "tests"
Requires-Dist: pytest-cov>=2.8.0; extra == "tests"
Requires-Dist: pytest-xdist>=2; extra == "tests"
Requires-Dist: pytest-mock>=3.7; extra == "tests"
Requires-Dist: pytest>=6; extra == "tests"
Requires-Dist: testfixtures>=6.11.0; extra == "tests"
Requires-Dist: towncrier>=24.7.0; extra == "tests"
Requires-Dist: types-Jinja2>=0.1.3; extra == "tests"
Requires-Dist: types-protobuf!=5.29.1.20250402,>=0.1.10; extra == "tests"
Provides-Extra: tutorials
Requires-Dist: h5py; extra == "tutorials"
Requires-Dist: requests; extra == "tutorials"
Provides-Extra: all
Requires-Dist: pillow; extra == "all"
Requires-Dist: pympler; extra == "all"
Requires-Dist: matplotlib; extra == "all"
Requires-Dist: sqlparse; extra == "all"
Requires-Dist: matplotlib; extra == "all"
Requires-Dist: pympler; extra == "all"
Requires-Dist: matplotlib; extra == "all"
Requires-Dist: aiosmtpd; extra == "all"
Requires-Dist: async_generator; extra == "all"
Requires-Dist: bandit>=1.7.0; extra == "all"
Requires-Dist: coverage>=7.9.0; extra == "all"
Requires-Dist: flake8-broken-line>=0.3.0; extra == "all"
Requires-Dist: flake8-bugbear>=21.0.0; extra == "all"
Requires-Dist: flake8-builtins>=1.5.0; extra == "all"
Requires-Dist: flake8-comprehensions>=3.5.0; extra == "all"
Requires-Dist: flake8-debugger>=4.0.0; extra == "all"
Requires-Dist: flake8-implicit-str-concat>=0.4; extra == "all"
Requires-Dist: flake8-mutable>=1.2.0; extra == "all"
Requires-Dist: flake8-simplify>=0.14.0; python_version < "3.14" and extra == "all"
Requires-Dist: flake8-type-checking; extra == "all"
Requires-Dist: flake8>=3.0.0; extra == "all"
Requires-Dist: mypy>=0.910; extra == "all"
Requires-Dist: pytest-asyncio!=0.23.*,>=0.21.2; extra == "all"
Requires-Dist: pytest-cov>=2.8.0; extra == "all"
Requires-Dist: pytest-xdist>=2; extra == "all"
Requires-Dist: pytest-mock>=3.7; extra == "all"
Requires-Dist: pytest>=6; extra == "all"
Requires-Dist: testfixtures>=6.11.0; extra == "all"
Requires-Dist: towncrier>=24.7.0; extra == "all"
Requires-Dist: types-Jinja2>=0.1.3; extra == "all"
Requires-Dist: types-protobuf!=5.29.1.20250402,>=0.1.10; extra == "all"
Requires-Dist: h5py; extra == "all"
Requires-Dist: requests; extra == "all"
Dynamic: license-file
